{
    "key": "group_68fa4d0774483",
    "title": "Block: Blog",
    "fields": [
        {
            "key": "field_69af2a0e08195",
            "label": "Block General Option",
            "name": "block_general_option",
            "aria-label": "",
            "type": "clone",
            "instructions": "",
            "required": 0,
            "conditional_logic": 0,
            "wrapper": {
                "width": "",
                "class": "",
                "id": ""
            },
            "clone": [
                "group_69aef8c3d5d44"
            ],
            "display": "seamless",
            "layout": "block",
            "prefix_label": 0,
            "prefix_name": 0
        },
        {
            "key": "field_68fa4d07eb2f7",
            "label": "Intro",
            "name": "intro",
            "aria-label": "",
            "type": "wysiwyg",
            "instructions": "",
            "required": 0,
            "conditional_logic": 0,
            "wrapper": {
                "width": "",
                "class": "",
                "id": ""
            },
            "default_value": "",
            "allow_in_bindings": 0,
            "tabs": "all",
            "toolbar": "full",
            "media_upload": 1,
            "delay": 0
        },
        {
            "key": "field_68fa4d73eb2f8",
            "label": "Posts Per Page",
            "name": "posts_per_page",
            "aria-label": "",
            "type": "select",
            "instructions": "Select number of posts per page.",
            "required": 0,
            "conditional_logic": 0,
            "wrapper": {
                "width": "50",
                "class": "",
                "id": ""
            },
            "choices": {
                "all": "All",
                "1": "1",
                "2": "2",
                "3": "3",
                "4": "4",
                "5": "5",
                "6": "6",
                "7": "7",
                "8": "8",
                "9": "9",
                "10": "10",
                "11": "11",
                "12": "12",
                "13": "13",
                "14": "14",
                "15": "15"
            },
            "default_value": 10,
            "return_format": "value",
            "multiple": 0,
            "allow_null": 0,
            "allow_in_bindings": 0,
            "ui": 0,
            "ajax": 0,
            "placeholder": "",
            "create_options": 0,
            "save_options": 0
        },
        {
            "key": "field_692995bf56d86",
            "label": "Choose Layout",
            "name": "choose_layout",
            "aria-label": "",
            "type": "radio",
            "instructions": "",
            "required": 0,
            "conditional_logic": 0,
            "wrapper": {
                "width": "50",
                "class": "",
                "id": ""
            },
            "choices": {
                "list_view": "List View",
                "grid_view": "Grid View"
            },
            "default_value": "",
            "return_format": "value",
            "allow_null": 0,
            "other_choice": 0,
            "allow_in_bindings": 0,
            "layout": "vertical",
            "save_other_choice": 0
        },
        {
            "key": "field_68fa4f0805b00",
            "label": "Categories",
            "name": "categories",
            "aria-label": "",
            "type": "taxonomy",
            "instructions": "Select a category or leave blank for all.",
            "required": 0,
            "conditional_logic": 0,
            "wrapper": {
                "width": "",
                "class": "",
                "id": ""
            },
            "taxonomy": "category",
            "add_term": 0,
            "save_terms": 0,
            "load_terms": 0,
            "return_format": "id",
            "field_type": "multi_select",
            "allow_null": 1,
            "allow_in_bindings": 0,
            "bidirectional": 0,
            "multiple": 0,
            "bidirectional_target": []
        },
        {
            "key": "field_68fa4fdd05b01",
            "label": "Exclude Categories",
            "name": "exclude_categories",
            "aria-label": "",
            "type": "taxonomy",
            "instructions": "Select a category to exclude.",
            "required": 0,
            "conditional_logic": 0,
            "wrapper": {
                "width": "",
                "class": "",
                "id": ""
            },
            "taxonomy": "category",
            "add_term": 0,
            "save_terms": 0,
            "load_terms": 0,
            "return_format": "id",
            "field_type": "multi_select",
            "allow_null": 1,
            "allow_in_bindings": 0,
            "bidirectional": 0,
            "multiple": 0,
            "bidirectional_target": []
        },
        {
            "key": "field_6929e56418694",
            "label": "Tags",
            "name": "tag",
            "aria-label": "",
            "type": "taxonomy",
            "instructions": "",
            "required": 0,
            "conditional_logic": 0,
            "wrapper": {
                "width": "",
                "class": "",
                "id": ""
            },
            "taxonomy": "post_tag",
            "add_term": 1,
            "save_terms": 0,
            "load_terms": 0,
            "return_format": "id",
            "field_type": "multi_select",
            "allow_null": 1,
            "allow_in_bindings": 0,
            "bidirectional": 0,
            "multiple": 0,
            "bidirectional_target": []
        },
        {
            "key": "field_68fa505705b02",
            "label": "Show Thumbnail",
            "name": "show_thumbnail",
            "aria-label": "",
            "type": "true_false",
            "instructions": "Display the post featured image.",
            "required": 0,
            "conditional_logic": 0,
            "wrapper": {
                "width": "50",
                "class": "",
                "id": ""
            },
            "message": "",
            "default_value": 1,
            "allow_in_bindings": 0,
            "ui_on_text": "",
            "ui_off_text": "",
            "ui": 1
        },
        {
            "key": "field_68fa508505b03",
            "label": "Show Excerpt",
            "name": "show_excerpt",
            "aria-label": "",
            "type": "true_false",
            "instructions": "Choose to show the excerpt.",
            "required": 0,
            "conditional_logic": 0,
            "wrapper": {
                "width": "50",
                "class": "",
                "id": ""
            },
            "message": "",
            "default_value": 1,
            "allow_in_bindings": 0,
            "ui_on_text": "",
            "ui_off_text": "",
            "ui": 1
        },
        {
            "key": "field_68fa50b005b04",
            "label": "Show Categories",
            "name": "show_categories",
            "aria-label": "",
            "type": "true_false",
            "instructions": "Choose to show the categories.",
            "required": 0,
            "conditional_logic": 0,
            "wrapper": {
                "width": "50",
                "class": "",
                "id": ""
            },
            "message": "",
            "default_value": 1,
            "allow_in_bindings": 0,
            "ui_on_text": "",
            "ui_off_text": "",
            "ui": 1
        },
        {
            "key": "field_68fa515505b06",
            "label": "Show Read More Link",
            "name": "show_read_more_link",
            "aria-label": "",
            "type": "true_false",
            "instructions": "Choose to show the Read More link.",
            "required": 0,
            "conditional_logic": 0,
            "wrapper": {
                "width": "50",
                "class": "",
                "id": ""
            },
            "message": "",
            "default_value": 1,
            "allow_in_bindings": 0,
            "ui_on_text": "",
            "ui_off_text": "",
            "ui": 1
        },
        {
            "key": "field_68fa513205b05",
            "label": "Show Date",
            "name": "show_date",
            "aria-label": "",
            "type": "true_false",
            "instructions": "Choose to show the date.",
            "required": 0,
            "conditional_logic": 0,
            "wrapper": {
                "width": "50",
                "class": "",
                "id": ""
            },
            "message": "",
            "default_value": 1,
            "allow_in_bindings": 0,
            "ui_on_text": "",
            "ui_off_text": "",
            "ui": 1
        },
        {
            "key": "field_68fa52f5efc66",
            "label": "Show Author Name",
            "name": "show_author_name",
            "aria-label": "",
            "type": "true_false",
            "instructions": "Choose to show the author.",
            "required": 0,
            "conditional_logic": 0,
            "wrapper": {
                "width": "50",
                "class": "",
                "id": ""
            },
            "message": "",
            "default_value": 0,
            "allow_in_bindings": 0,
            "ui_on_text": "",
            "ui_off_text": "",
            "ui": 1
        },
        {
            "key": "field_69298ce009746",
            "label": "Show Pagination",
            "name": "show_pagination",
            "aria-label": "",
            "type": "true_false",
            "instructions": "",
            "required": 0,
            "conditional_logic": 0,
            "wrapper": {
                "width": "50",
                "class": "",
                "id": ""
            },
            "message": "",
            "default_value": 1,
            "allow_in_bindings": 0,
            "ui_on_text": "",
            "ui_off_text": "",
            "ui": 1
        }
    ],
    "location": [
        [
            {
                "param": "block",
                "operator": "==",
                "value": "acf/blog-block"
            }
        ]
    ],
    "menu_order": 0,
    "position": "normal",
    "style": "default",
    "label_placement": "top",
    "instruction_placement": "label",
    "hide_on_screen": "",
    "active": true,
    "description": "",
    "show_in_rest": 0,
    "display_title": "",
    "modified": 1774354101
}